venv_cleaner/__init__.py
venv_cleaner/__main__.py
venv_cleaner/app.py
cleaner_for_venv-0.1.1.dist-info/METADATA
cleaner_for_venv-0.1.1.dist-info/WHEEL
cleaner_for_venv-0.1.1.dist-info/entry_points.txt
cleaner_for_venv-0.1.1.dist-info/RECORD
