Metadata-Version: 2.4
Name: cleaner-for-venv
Version: 0.1.1
Summary: A TUI app to find and delete Python virtual environments
Project-URL: Homepage, https://github.com/ajayn/venv-cleaner
Project-URL: Repository, https://github.com/ajayn/venv-cleaner
Author: Ajay N
License-Expression: MIT
Keywords: cleanup,textual,tui,venv,virtual-environment
Classifier: Development Status :: 4 - Beta
Classifier: Environment :: Console
Classifier: Intended Audience :: Developers
Classifier: License :: OSI Approved :: MIT License
Classifier: Operating System :: OS Independent
Classifier: Programming Language :: Python :: 3
Classifier: Programming Language :: Python :: 3.10
Classifier: Programming Language :: Python :: 3.11
Classifier: Programming Language :: Python :: 3.12
Classifier: Topic :: Utilities
Requires-Python: >=3.10
Requires-Dist: textual>=0.40.0
